Workbook

Sheet INVOICE
A8: INVOICE
A10: INVOICE NUMBER :
A11: Date | D11: : | E11: 45855
A13: SELLERS
A14: Akerko Su Urunleri Sanayi Balikcilik Nak. Tar. Urn. Yet. Tic. Ltd. Sti
A15: MERKEZ MAH. AKMAZ KÜME EVL. NO: 83 ÇARŞIBAŞI/TRABZON
A16: VAT :CARŞIBASI MM-023 030 23 43
A17: T: +90 462 821 39 90 F: +90 462 821 21 44
A19: MESSRS
A20: OOO “MOREODOR”
A21: 117292, Profsoyuznaya st. 3, office 412, Moscow, RUSSIA
A22: INN(TVA): 7727734159
A24: CONTRACT NUMBER / DATE : 220521 dd 20.05.22
A25: DELIVERY TERMS: DAP MOSCOW
A26: PAYMENT TERMS:100% PAYMENT BEFORE ARRIVING AT COLDSTORE
A27: TRUCK NUMBER: | E27: 61 ZZ 530 /61 AFY 786
A28: DESCRIPTION OF GOODS
A29: COUNTRY OF ORIGIN | O29: : | P29: TURKEY
A30: ITEM | O30: : | P30: FROZEN RAINBOW TROUT WR IQF (ONCORHYNCHUS MYKISS)
A31: CUSTOMS CODE: 030314
A32: SIZE | H32: QUANTITY OF NET WEIGHT | R32: QUANTITY OF CARTONS | AB32: PRICE PER CARTON | AP32: AMOUNT
A33: 0,5-0,8 KG | H33: 19213.72 | N33: KG | R33: 745 | AA33: 109.60847 | AH33: USD | AP33: =R33*AA33 -> 81658.309 | AS33: USD
N40: TOTAL: | AO40: : | AP40: =SUM(AP33:AR39) -> 81658.309 | AS40: USD
A48: BANK NAME | J48: : | K48: Ziraat Bankası Trabzon Girişimci Şubesi
A49: IBAN | J49: : | K49: TR 5900 0100 2107 4820 9282 5006
A50: SWIFT CODE | J50: : | K50: TCZBTR2A
A51: PRODUCER NAME | J51: : | K51: Akerko Su Urunleri Sanayi Balikcilik Nak. Tar. Urun. Yet. Tic. Ltd. Sti
A52: EXPORT NUMBER | J52: : | K52: TR 61-0024

Sheet PAC.LIST
A5: PACKING LIST
H7: =+INVOICE!E11 -> 45855
A8: SHIPPER:
A9: Akerko Su Urunleri Sanayi Balikcilik Nak. Tar. Urun. Yet. Tic. Ltd. Sti
A10: Merkez Mahallesi Akmaz Kume Evleri № 83 Carsibasi-Trabzon
A13: RECEIVER:
A14: OOO “MOREODOR”
A15: 117292, Profsoyuznaya st. 3, office 412, Moscow, RUSSIA
A16: INN(TVA): 7727734159
A18: TOTAL NET WEIGHT KGS | B18: =E32 -> 19213.72
A19: PALLET WEIGHT KGS | B19: =J32*15 -> 465
A20: TOTAL BOXES | B20: =D32 -> 745
A21: TOTAL GROSS WEIGHT KGS | B21: =F32 -> 20528.07
A22: PALLET PCS | B22: =+J32 -> 31
A23: TRUCK PLATE NUMBER | B23: =INVOICE!E27 -> 61 ZZ 530 /61 AFY 786
A24: PRODUCER FACTORY NO | B24: TR 61-0024
A25: ORIGIN OF GOODS | B25: TURKEY
A27: DESCRIPTION OF THE GOODS | C27: CUSTOMS CODE | D27: NO. BOX | E27: NET WEIGHT KGS | F27: GROSS WEIGHT KGS | G27: PRODUCTION DATE | H27: NET WEIGHT WITH GLAZING KGS | I27: GROSS WEIGHT WITH PALLETS KGS | J27: PALLET NO
A28: FROZEN RAINBOW TROUT WR, IQF (ONCORHYNCHUS MYKISS) 0,5-0,8 KG | C28: 030314 | D28: =+INVOICE!R33 -> 745 | E28: =+INVOICE!H33 -> 19213.72 | F28: =H28+(D28*1.3) -> 20528.07 | G28: 45819 | H28: =ROUND(E28+(E28*0.018),2) -> 19559.57 | I28: =F28+15*J28 -> 20993.07 | J28: 31
A32: TOTAL | D32: =SUM(D28:D31) -> 745 | E32: =SUM(E28:E31) -> 19213.72 | F32: =SUM(F28:F31) -> 20528.07 | H32: =SUM(H28:H31) -> 19559.57 | I32: =SUM(I28:I31) -> 20993.07 | J32: =SUM(J28:J31) -> 31
G33: EXPIRY DATE:
G34: 24 MONTHS

Sheet QUAL.CER.
A8: QUALITY CERTIFICATE
E9: OOO “MOREODOR”
E10: 117292, Profsoyuznaya st. 3, office 412, Moscow, RUSSIA
E11: INN(TVA): 7727734159
A16: DATE | B16: =+INVOICE!E11 -> 45855
A17: TRUCK PLATE NUMBER | B17: =+PAC.LIST!B23 -> 61 ZZ 530 /61 AFY 786
A18: COUNTRY OF ORIGIN | B18: TURKEY
A19: FACTORY EU APPROVAL NUMBER | B19: TR 61-0024
A20: FROM | B20: TRABZON / TURKEY
A21: TO | B21: MOSCOW / RUSSIA
A25: DESCRIPTION OF THE GOODS | B25: NO. BOX | C25: NET WEIGHT KGS | D25: GROSS WEIGHT +PL KGS | E25: PRODUCTION DATE | F25: EXPIRY DATE
A26: FROZEN RAINBOW TROUT WR, IQF (ONCORHYNCHUS MYKISS) 0,5-0,8 KG | B26: =+PAC.LIST!D28 -> 745 | C26: =+PAC.LIST!E28 -> 19213.72 | D26: =+PAC.LIST!I28 -> 20993.07 | E26: =+PAC.LIST!G28 -> 45819 | F26: 24 MONTHS
A31: TOTAL | B31: =SUM(B26:B30) -> 745 | C31: =SUM(C26:C30) -> 19213.72 | D31: =SUM(D26:D30) -> 20993.07
A33: TO BE KEPT UNDER TEMPERATURE -18C
A34: CERTIFY THAT ABOVE MENTIONED PRODUCTS ARE FIT FOR HUMAN CONSUMPTION

Sheet PRICE LIST
B7: TO WHOM IT MAY CONSERN
E8: PRICE LIST
B9: DATE | C9: 45855 | E9: VALID UNTIL | F9: 45899
B13: TERM OF DELIVERY: DAP MOSCOW
B14: TRANSPORTATION BY: TRUCK
B15: ENTERPRICE NUMBER:TR 61-0024
B16: PRODUCER: | C16: Akerko Su Urunleri Sanayi Balikcilik Nak. Tar. Urun. Yet. Tic. Ltd. Sti
C18: ÜRÜN AÇIKLAMASI | F18: FİYAT
C19: DESCRIPTION OF GOODS | F19: PRICE USD/CARTON BOX
B20: 1 | C20: FROZEN RAINBOW TROUT WR (Oncorhynchus mykıss) 0,5-0,8 KG | F20: =INVOICE!AA33 -> 109.60847

Sheet Sayfa1
A4: 4.25 | B4: =INVOICE!H33 -> 19213.72
A5: =+(B4*A4) -> 81658.31 | B5: 745
A6: =+A5/B5 -> 109.60847 | B6: =+A5/B4 -> 4.25
